[
  {
    "id": 1,
    "title": "Wandering Son",
    "aka": "Hourou Musuko",
    "episodes": 11,
    "rating": 10,
    "review": "Brilliant, touching, beautiful, heartfelt depiction of trans kids growing up in a not always kind world. Read the manga, seriously, read it.",
    "genre": ["Slice+of+Life", "Shoujo", "Coming+of+Age"]
  },
  {
    "id": 2,
    "title": "Kids on the Slope",
    "aka": "",
    "episodes": 12,
    "rating": 10,
    "review": "You wouldn't expect it to, but it becomes a very touching and emotional series with literal heartstopping moments. Jazz it up and watch it, seriously.",
    "genre": ["Slice+of+Life", "Shonen", "Romance", "Coming+of+Age"]
  }
]
